relationship/__init__.py
relationship/cache.py
relationship/id_.py
relationship/map.py
relationship/mode.py
relationship/options.py
relationship/relationship.py
relationship/selector.py
relationship/unit.py
relationship/data/__init__.py
relationship/data/branch.py
relationship/data/input.py
relationship/data/main.py
relationship/data/multiple.py
relationship/data/pair.py
relationship/data/prefix.py
relationship/data/sort.py
relationship/locale_/__init__.py
relationship/locale_/guangdong.py
relationship/locale_/north.py
relationship/rule/__init__.py
relationship/rule/expression.py
relationship/rule/filter.py
relationship/rule/replace.py
relationship/rule/similar.py
relationship/tests/bench_test.py
relationship/tests/unit_test.py
python3_relationship-0.1.3.dist-info/METADATA
python3_relationship-0.1.3.dist-info/WHEEL
python3_relationship-0.1.3.dist-info/licenses/LICENSE
python3_relationship-0.1.3.dist-info/RECORD
