Metadata-Version: 2.4
Name: python3-relationship
Version: 0.1.3
Summary: Chinese Kinship Calculator - Used for calculating family titles, kinship addresses, and generational relationships.
Project-URL: Homepage, https://github.com/young2j/relationship/tree/main/relationship-py
Project-URL: Documentation, https://github.com/young2j/relationship/tree/main/relationship-py/README.md
Project-URL: Repository, https://github.com/young2j/relationship.git
Author-email: young2j <173371929@qq.com>
License-Expression: MIT
License-File: LICENSE
Keywords: calculator,kinship,relationship
Classifier: Natural Language :: Chinese (Simplified)
Classifier: Programming Language :: Python
Requires-Python: >=3.11
